soil_capacity_wilting/__init__.py
soil_capacity_wilting/soil_capacity_wilting.py
soil_capacity_wilting/version.txt
soil_capacity_wilting-1.2.0.dist-info/licenses/LICENSE
soil_capacity_wilting-1.2.0.dist-info/METADATA
soil_capacity_wilting-1.2.0.dist-info/WHEEL
soil_capacity_wilting-1.2.0.dist-info/top_level.txt
soil_capacity_wilting-1.2.0.dist-info/RECORD
